ultra_mem/__init__.py
ultra_mem/ultra_mem.py
ultra_mem-0.1.2.dist-info/METADATA
ultra_mem-0.1.2.dist-info/WHEEL
ultra_mem-0.1.2.dist-info/licenses/LICENSE
ultra_mem-0.1.2.dist-info/RECORD
