Metadata-Version: 2.4
Name: ultra-mem
Version: 0.1.2
Summary: UltraMem
Project-URL: Homepage, https://pypi.org/project/ultra-mem/
Project-URL: Repository, https://github.com/lucidrains/ultra-mem
Author-email: Phil Wang <lucidrains@gmail.com>
License: MIT License
License-File: LICENSE
Keywords: artificial intelligence,deep learning,memory
Classifier: Development Status :: 4 - Beta
Classifier: Intended Audience :: Developers
Classifier: License :: OSI Approved :: MIT License
Classifier: Programming Language :: Python :: 3.9
Classifier: Topic :: Scientific/Engineering :: Artificial Intelligence
Requires-Python: >=3.9
Requires-Dist: einops>=0.8.1
Requires-Dist: einx>=0.3.0
Requires-Dist: torch>=2.4
Provides-Extra: examples
Provides-Extra: test
Requires-Dist: pytest; extra == 'test'
